mopidy_tidal/__init__.py
mopidy_tidal/backend.py
mopidy_tidal/context.py
mopidy_tidal/ext.conf
mopidy_tidal/full_models_mappers.py
mopidy_tidal/helpers.py
mopidy_tidal/library.py
mopidy_tidal/login_hack.py
mopidy_tidal/lru_cache.py
mopidy_tidal/playback.py
mopidy_tidal/playlists.py
mopidy_tidal/ref_models_mappers.py
mopidy_tidal/search.py
mopidy_tidal/utils.py
mopidy_tidal/web_auth_server.py
mopidy_tidal-0.3.13.dist-info/METADATA
mopidy_tidal-0.3.13.dist-info/WHEEL
mopidy_tidal-0.3.13.dist-info/entry_points.txt
mopidy_tidal-0.3.13.dist-info/licenses/LICENSE
mopidy_tidal-0.3.13.dist-info/RECORD
