Metadata-Version: 2.4
Name: mopidy-tidal
Version: 0.3.13
Summary: Mopidy Extension for Tidal music service integration.
License: Apache-2.0
License-File: LICENSE
Author: Johannes Linde
Author-email: tehkillerbee@users.noreply.github.com
Requires-Python: >=3.11,<4.0
Classifier: Environment :: No Input/Output (Daemon)
Classifier: Intended Audience :: End Users/Desktop
Classifier: License :: OSI Approved :: Apache Software License
Classifier: Operating System :: OS Independent
Classifier: Programming Language :: Python :: 3
Classifier: Topic :: Multimedia :: Sound/Audio :: Players
Requires-Dist: Mopidy (>=3.0)
Requires-Dist: tidalapi (>=0.8.10)
Project-URL: Repository, https://github.com/EbbLabs/mopidy-tidal
